terrible_ideas.py
terrible_ideas-0.8.0.dist-info/WHEEL
terrible_ideas-0.8.0.dist-info/METADATA
terrible_ideas-0.8.0.dist-info/RECORD
