Metadata-Version: 2.1
Name: terrible-ideas
Version: 0.8.0
Summary: Frequently asked-for missing anti-features
License: WTFPL
Author: L3viathan
Author-email: git@l3vi.de
Requires-Python: >=3.7,<4.0
Classifier: License :: Other/Proprietary License
Classifier: Programming Language :: Python :: 3
Classifier: Programming Language :: Python :: 3.10
Classifier: Programming Language :: Python :: 3.7
Classifier: Programming Language :: Python :: 3.8
Classifier: Programming Language :: Python :: 3.9
Requires-Dist: fishhook (>=0.1.4,<0.2.0)
Requires-Dist: spelcheck (>=0.3.1,<0.4.0)
